pyKoLesky/__init__.py
pyKoLesky/cholesky.py
pyKoLesky/maxheap.py
pyKoLesky/ordering.py
pykolesky-0.1.6.dist-info/METADATA
pykolesky-0.1.6.dist-info/WHEEL
pykolesky-0.1.6.dist-info/RECORD
