Metadata-Version: 2.1
Name: pyKoLesky
Version: 0.1.6
Summary: A Python implementation for sparse Cholesky decomposition of covariance matrices.
Home-page: https://github.com/yangx0e/pyKoLesky
License: CC-BY-NC 4.0
Keywords: Cholesky
Author: Xianjin Yang
Classifier: License :: Other/Proprietary License
Classifier: Programming Language :: Python :: 2
Classifier: Programming Language :: Python :: 2.7
Classifier: Programming Language :: Python :: 3
Classifier: Programming Language :: Python :: 3.4
Classifier: Programming Language :: Python :: 3.5
Classifier: Programming Language :: Python :: 3.6
Classifier: Programming Language :: Python :: 3.7
Classifier: Programming Language :: Python :: 3.8
Classifier: Programming Language :: Python :: 3.9
Classifier: Programming Language :: Python :: 3.10
Classifier: Programming Language :: Python :: 3.11
Classifier: Programming Language :: Python :: 3.12
Classifier: Programming Language :: Python :: 3.13
Project-URL: Repository, https://github.com/yangx0e/pyKoLesky
